djangomails/__init__.py
djangomails/asgi.py
djangomails/settings.py
djangomails/test_settings.py
djangomails/urls.py
djangomails/wsgi.py
email_service/__init__.py
email_service/admin.py
email_service/apps.py
email_service/models.py
email_service/tests.py
email_service/utils.py
email_service/views.py
email_service/migrations/0001_initial.py
email_service/migrations/__init__.py
django_mails-1.1.0.dist-info/LICENSE
django_mails-1.1.0.dist-info/METADATA
django_mails-1.1.0.dist-info/WHEEL
django_mails-1.1.0.dist-info/top_level.txt
django_mails-1.1.0.dist-info/RECORD
