Metadata-Version: 2.1
Name: django-mails
Version: 1.1.0
Summary: A Django Library to Send Simple/HTML Emails
Home-page: https://github.com/Hashtrust-technology-private-limited/django-email-service
Author: Hashtrust Technologies Private Limited
Author-email: support@hashtrust.in
License: MIT License
Classifier: Environment :: Web Environment
Classifier: Framework :: Django :: 4.1
Classifier: Intended Audience :: Developers
Classifier: License :: OSI Approved :: MIT License
Classifier: Operating System :: OS Independent
Classifier: Programming Language :: Python
Classifier: Programming Language :: Python :: 3
Classifier: Programming Language :: Python :: 3 :: Only
Classifier: Programming Language :: Python :: 3.9
Classifier: Programming Language :: Python :: 3.10
Classifier: Topic :: Communications :: Chat
Requires-Python: >=3.9
License-File: LICENSE
Requires-Dist: django
Requires-Dist: django-ckeditor
Requires-Dist: django-js-asset
Requires-Dist: html2text
Requires-Dist: Jinja2
Requires-Dist: MarkupSafe
Requires-Dist: sqlparse
